{
  "designerVersion" : "1.8.29",
  "previousDesignerVersion" : "1.7.49",
  "id" : "UploadProofOfDomicile",
  "name" : "UploadProofOfDomicile",
  "lastUpdate" : 1552324465154,
  "rows" : [ [ {
    "type" : "component",
    "dimension" : {
      "xs" : 12,
      "sm" : 12,
      "md" : 12,
      "lg" : 12
    },
    "propertyValues" : {
      "cssClasses" : {
        "type" : "constant",
        "value" : ""
      },
      "hidden" : {
        "type" : "constant",
        "value" : false
      },
      "text" : {
        "type" : "interpolation",
        "value" : "Upload your proof of domicile"
      },
      "level" : {
        "type" : "constant",
        "value" : "Level 1"
      },
      "alignment" : {
        "type" : "constant",
        "value" : "left"
      }
    },
    "reference" : "e99a79f1-a3f7-4123-81fc-a08205d01385",
    "hasValidationError" : false,
    "id" : "pbTitle"
  } ], [ {
    "type" : "formContainer",
    "dimension" : {
      "xs" : 12,
      "sm" : 12,
      "md" : 12,
      "lg" : 12
    },
    "propertyValues" : {
      "cssClasses" : {
        "type" : "constant",
        "value" : ""
      },
      "hidden" : {
        "type" : "constant",
        "value" : false
      }
    },
    "reference" : "33cdd76d-304d-4fc1-82cd-5e6eaa8bf5bc",
    "hasValidationError" : false,
    "id" : "pbFormContainer",
    "container" : {
      "type" : "container",
      "dimension" : {
        "xs" : 12
      },
      "propertyValues" : { },
      "reference" : "a18b623c-27f5-4a84-bcdb-229325ed6bfc",
      "hasValidationError" : false,
      "id" : "pbContainer",
      "rows" : [ [ {
        "type" : "component",
        "dimension" : {
          "xs" : 12,
          "sm" : 12,
          "md" : 12,
          "lg" : 12
        },
        "propertyValues" : {
          "cssClasses" : {
            "type" : "constant",
            "value" : ""
          },
          "hidden" : {
            "type" : "constant",
            "value" : false
          },
          "required" : {
            "type" : "constant",
            "value" : true
          },
          "labelHidden" : {
            "type" : "constant",
            "value" : true
          },
          "label" : {
            "type" : "interpolation",
            "value" : "Default label"
          },
          "labelPosition" : {
            "type" : "constant",
            "value" : "top"
          },
          "labelWidth" : {
            "type" : "constant",
            "value" : 4
          },
          "placeholder" : {
            "type" : "interpolation"
          },
          "url" : {
            "type" : "constant",
            "value" : "../API/formFileUpload"
          },
          "value" : {
            "type" : "variable",
            "value" : "data.proofOfDomicileInput"
          },
          "errorContent" : {
            "type" : "variable",
            "value" : ""
          }
        },
        "reference" : "b5342e49-e2da-45f0-997a-eae09209effd",
        "hasValidationError" : false,
        "id" : "pbUpload"
      } ], [ {
        "type" : "component",
        "dimension" : {
          "xs" : 12,
          "sm" : 12,
          "md" : 12,
          "lg" : 12
        },
        "propertyValues" : {
          "cssClasses" : {
            "type" : "constant",
            "value" : ""
          },
          "hidden" : {
            "type" : "constant",
            "value" : false
          },
          "disabled" : {
            "type" : "constant",
            "value" : false
          },
          "label" : {
            "type" : "interpolation",
            "value" : "Submit"
          },
          "alignment" : {
            "type" : "constant",
            "value" : "center"
          },
          "buttonStyle" : {
            "type" : "constant",
            "value" : "primary"
          },
          "action" : {
            "type" : "constant",
            "value" : "POST"
          },
          "url" : {
            "type" : "interpolation",
            "value" : "/bonita/API/bpm/userTask/{{taskId}}/execution"
          },
          "dataToSend" : {
            "type" : "expression",
            "value" : "data"
          },
          "dataFromSuccess" : {
            "type" : "variable",
            "value" : "result"
          },
          "dataFromError" : {
            "type" : "variable",
            "value" : "result"
          },
          "targetUrlOnSuccess" : {
            "type" : "interpolation",
            "value" : "/bonita/apps/bonita-bank/openning/?fileref={{caseId}}"
          },
          "collectionToModify" : {
            "type" : "variable"
          },
          "collectionPosition" : {
            "type" : "constant",
            "value" : "Last"
          },
          "valueToAdd" : {
            "type" : "constant"
          },
          "removeItem" : {
            "type" : "variable"
          }
        },
        "reference" : "63070d6c-0920-4ea0-b3a9-01ae3e7825eb",
        "hasValidationError" : false,
        "id" : "pbButton"
      } ] ]
    }
  } ], [ {
    "type" : "component",
    "dimension" : {
      "xs" : 12,
      "sm" : 12,
      "md" : 12,
      "lg" : 12
    },
    "propertyValues" : {
      "cssClasses" : {
        "type" : "constant",
        "value" : ""
      },
      "hidden" : {
        "type" : "constant",
        "value" : true
      },
      "allowHTML" : {
        "type" : "constant",
        "value" : true
      },
      "text" : {
        "type" : "interpolation",
        "value" : "result: {{result | json}}"
      },
      "alignment" : {
        "type" : "constant",
        "value" : "left"
      }
    },
    "reference" : "bca83d74-4d32-4360-8ce8-3bd7c522c136",
    "hasValidationError" : false,
    "id" : "pbText"
  } ] ],
  "assets" : [ {
    "id" : "becfafea-2c94-467e-9263-1899b07a4c95",
    "name" : "localization.json",
    "type" : "json",
    "order" : 0,
    "external" : false
  }, {
    "id" : "92dd6783-ded5-4ae7-a51c-95b5d5feb8d7",
    "name" : "style.css",
    "type" : "css",
    "order" : 0,
    "external" : false
  } ],
  "inactiveAssets" : [ ],
  "data" : {
    "data" : {
      "type" : "json",
      "value" : "{\"proofOfDomicileInput\": null}",
      "exposed" : false
    },
    "taskId" : {
      "type" : "urlparameter",
      "value" : "taskId",
      "exposed" : false
    },
    "result" : {
      "type" : "json",
      "value" : "{}",
      "exposed" : false
    },
    "caseId" : {
      "type" : "urlparameter",
      "value" : "caseId",
      "exposed" : false
    }
  },
  "hasValidationError" : false,
  "uuid" : "e0856ea6-cafb-4770-a6ed-4dda96a42ce6",
  "type" : "page",
  "description" : "Page generated with Bonita UI designer",
  "displayName" : "UploadProofOfDomicile"
}